topy/__init__.py
topy/retf.txt
topy/topy.py
topy-1.0.1.dist-info/LICENSE.txt
topy-1.0.1.dist-info/METADATA
topy-1.0.1.dist-info/WHEEL
topy-1.0.1.dist-info/entry_points.txt
topy-1.0.1.dist-info/top_level.txt
topy-1.0.1.dist-info/RECORD
