Metadata-Version: 2.1
Name: topy
Version: 1.0.1
Summary: Fixes typos in text using regular expressions, based on RegExTypoFix from Wikipedia
Home-page: https://github.com/intgr/topy
Author: Marti Raudsepp
Author-email: marti@juffo.org
License: MIT, CC-BY-SA
Download-URL: https://pypi.python.org/pypi/topy/
Keywords: typo spelling grammar text
Platform: any
Classifier: Development Status :: 5 - Production/Stable
Classifier: Environment :: Console
Classifier: Intended Audience :: Developers
Classifier: License :: OSI Approved :: MIT License
Classifier: Programming Language :: Python :: 3.5
Classifier: Programming Language :: Python :: 3.6
Classifier: Programming Language :: Python :: 3.7
Classifier: Programming Language :: Python :: 3.8
Classifier: Programming Language :: Python :: 3.9
Classifier: Topic :: Documentation
Classifier: Topic :: Software Development :: Quality Assurance
Classifier: Topic :: Text Processing :: Filters
Requires-Dist: regex (>=2016.07.14)
Requires-Dist: beautifulsoup4
